patreklib/IG_info.py
patreklib/__init__.py
patreklib-0.0.1.dist-info/METADATA
patreklib-0.0.1.dist-info/WHEEL
patreklib-0.0.1.dist-info/top_level.txt
patreklib-0.0.1.dist-info/RECORD
